[{"اسم الزيت": "اكسترا جيت1 ك", "الرصيد الافتتاحي": 0}, {"اسم الزيت": "اكسترا سوبر 1ك", "الرصيد الافتتاحي": 0}, {"اسم الزيت": "اكسترا سوبر 4ك", "الرصيد الافتتاحي": 8}, {"اسم الزيت": "الترا7 4ك", "الرصيد الافتتاحي": 7}, {"اسم الزيت": "باور 1ك", "الرصيد الافتتاحي": 38}, {"اسم الزيت": "بتروتوك 1.6لتر", "الرصيد الافتتاحي": 0}, {"اسم الزيت": "بتروتوك 1.75 لتر", "الرصيد الافتتاحي": 0}, {"اسم الزيت": "بترومين مونو  1ك", "الرصيد الافتتاحي": 0}, {"اسم الزيت": "بترومين مونو  4ك", "الرصيد الافتتاحي": 0}, {"اسم الزيت": "تروس 140 16 ك", "الرصيد الافتتاحي": 102}, {"اسم الزيت": "تروس 140 4ك", "الرصيد الافتتاحي": 43}, {"اسم الزيت": "تروس 140 W85-5-G1  - (1ك)", "الرصيد الافتتاحي": 0}, {"اسم الزيت": "تروس 140 W85-5-G1  - (4ك)", "الرصيد الافتتاحي": 0}, {"اسم الزيت": "تروس 85 1ك", "الرصيد الافتتاحي": 0}, {"اسم الزيت": "تروس 85 4ك", "الرصيد الافتتاحي": 0}, {"اسم الزيت": "تروس 90 16ك", "الرصيد الافتتاحي": 2}, {"اسم الزيت": "تروس 90 1ك", "الرصيد الافتتاحي": 0}, {"اسم الزيت": "تروس 90 4ك", "الرصيد الافتتاحي": 11}, {"اسم الزيت": "دكسرون || مستورد 1ك", "الرصيد الافتتاحي": 0}, {"اسم الزيت": "دكسرون ||| مستورد 1ك", "الرصيد الافتتاحي": 0}, {"اسم الزيت": "دلفاك 20 ك", "الرصيد الافتتاحي": 2}, {"اسم الزيت": "دلفاك 4 ك", "الرصيد الافتتاحي": 0}, {"اسم الزيت": "دلفاك 5 ك", "الرصيد الافتتاحي": 0}, {"اسم الزيت": "ديو 40 (20لتر)", "الرصيد الافتتاحي": 2}, {"اسم الزيت": "ديو 40 (4ك)", "الرصيد الافتتاحي": 117}, {"اسم الزيت": "ديو 40 (5ك)", "الرصيد الافتتاحي": 147}, {"اسم الزيت": "ديو 50 (16لتر)", "الرصيد الافتتاحي": 0}, {"اسم الزيت": "ديو 50 (1ك)", "الرصيد الافتتاحي": 736}, {"اسم الزيت": "ديومين 20 لتر", "الرصيد الافتتاحي": 5}, {"اسم الزيت": "زيت مبرد 33% 4ك", "الرصيد الافتتاحي": 0}, {"اسم الزيت": "زيت مبرد 50% 4ك", "الرصيد الافتتاحي": 0}, {"اسم الزيت": "سبيد بورد 1 ك", "الرصيد الافتتاحي": 0}, {"اسم الزيت": "سوبر 1000 / 1", "الرصيد الافتتاحي": 5}, {"اسم الزيت": "سوبر 1000 / 4", "الرصيد الافتتاحي": 0}, {"اسم الزيت": "سوبر الترا", "الرصيد الافتتاحي": 1}, {"اسم الزيت": "سوبر ديزل 50 (20 لتر)", "الرصيد الافتتاحي": 60}, {"اسم الزيت": "سوبر ديزل 50 (4ك)", "الرصيد الافتتاحي": 0}, {"اسم الزيت": "سوبر ديزل 50 (5ك)", "الرصيد الافتتاحي": 40}, {"اسم الزيت": "سوبر سينثيتيك 4ك", "الرصيد الافتتاحي": 0}, {"اسم الزيت": "سوبر سينثيتيك1ك", "الرصيد الافتتاحي": 0}, {"اسم الزيت": "سوبر سينثيتيك3ك", "الرصيد الافتتاحي": 0}, {"اسم الزيت": "سوبر فليت ماستر  20 لتر", "الرصيد الافتتاحي": 0}, {"اسم الزيت": "سوبر فليت ماستر1ك", "الرصيد الافتتاحي": 0}, {"اسم الزيت": "سوبر فليت ماستر5ك", "الرصيد الافتتاحي": 0}, {"اسم الزيت": "شحم 1", "الرصيد الافتتاحي": 2}, {"اسم الزيت": "شحم 1/2", "الرصيد الافتتاحي": 1}, {"اسم الزيت": "شحم الاهلية 0.5ك", "الرصيد الافتتاحي": 0}, {"اسم الزيت": "شحم الاهلية 0.5ك الأصفر", "الرصيد الافتتاحي": 0}, {"اسم الزيت": "شحم الاهلية 1ك", "الرصيد الافتتاحي": 8}, {"اسم الزيت": "شحم ام بي 3 0.5ك", "الرصيد الافتتاحي": 0}, {"اسم الزيت": "شحم ام بي 3 16ك", "الرصيد الافتتاحي": 0}, {"اسم الزيت": "شحم ام بي 3 1ك", "الرصيد الافتتاحي": 3}, {"اسم الزيت": "شحم ام بي 3 3ك", "الرصيد الافتتاحي": 0}, {"اسم الزيت": "شحم ام بي3 200جم", "الرصيد الافتتاحي": 0}, {"اسم الزيت": "فلت ماستر", "الرصيد الافتتاحي": 0}, {"اسم الزيت": "مخصوص 20", "الرصيد الافتتاحي": 0}, {"اسم الزيت": "مخصوص 5", "الرصيد الافتتاحي": 0}, {"اسم الزيت": "موبيل 1000 1ك", "الرصيد الافتتاحي": 8}, {"اسم الزيت": "موبيل 1000 4ك", "الرصيد الافتتاحي": 0}, {"اسم الزيت": "هيدرولك 37-16 ك", "الرصيد الافتتاحي": 4}, {"اسم الزيت": "هيدرولك 46-16 ك", "الرصيد الافتتاحي": 7}, {"اسم الزيت": "هيدرولك 68-16 ك", "الرصيد الافتتاحي": 6}]